epijats/__init__.py
epijats/__main__.py
epijats/_version.py
epijats/biblio.py
epijats/condition.py
epijats/document.py
epijats/dom.py
epijats/elements.py
epijats/eprint.py
epijats/jats.py
epijats/jinja.py
epijats/math.py
epijats/metadata.py
epijats/py.typed
epijats/tree.py
epijats/typeshed.py
epijats/util.py
epijats/webstract.py
epijats/csl/abridged.csl
epijats/csl/full-preview.csl
epijats/parse/__init__.py
epijats/parse/back.py
epijats/parse/baseprint.py
epijats/parse/body.py
epijats/parse/content.py
epijats/parse/front.py
epijats/parse/htmlish.py
epijats/parse/kit.py
epijats/parse/math.py
epijats/parse/table.py
epijats/parse/tree.py
epijats/static/Open_Access_logo_PLoS_transparent.svg
epijats/static/PDF_file_icon.svg
epijats/static/article.css
epijats/static/cc.svg
epijats/static/orcid.svg
epijats/static/printstrap.css
epijats/static/webpaper.css
epijats/templates/article.html.jinja
epijats/templates/base.html.jinja
epijats/templates/issues.html.jinja
epijats/templates/epijats/_common.html.jinja
epijats/templates/epijats/lyon.html.jinja
epijats/xml/__init__.py
epijats/xml/baseprint.py
epijats/xml/format.py
epijats/xml/html.py
epijats-3.2.1.dist-info/LICENSE
epijats-3.2.1.dist-info/METADATA
epijats-3.2.1.dist-info/WHEEL
epijats-3.2.1.dist-info/entry_points.txt
epijats-3.2.1.dist-info/top_level.txt
epijats-3.2.1.dist-info/RECORD
