Metadata-Version: 2.1
Name: epijats
Version: 3.2.1
Summary: E-Printing Identified JATS
Author-email: Castedo Ellerman <castedo@castedo.com>
License: MIT License
Project-URL: Homepage, https://gitlab.com/perm.pub/epijats
Classifier: Programming Language :: Python :: 3
Classifier: License :: OSI Approved :: MIT License
Classifier: Operating System :: POSIX
Classifier: Development Status :: 4 - Beta
Classifier: Topic :: Text Processing :: Markup :: XML
Requires-Python: >=3.11
License-File: LICENSE
Requires-Dist: citeproc-py >=0.7
Requires-Dist: hidos >=2.6
Requires-Dist: jinja2
Requires-Dist: lxml
Provides-Extra: pdf
Requires-Dist: weasyprint >=60.2 ; extra == 'pdf'
